streamlit_list_with_loader/__init__.py
streamlit_list_with_loader/frontend/index.html
streamlit_list_with_loader/frontend/main.js
streamlit_list_with_loader/frontend/streamlit-component-lib.js
streamlit_list_with_loader/frontend/style.css
streamlit_list_with_loader-0.1.3.dist-info/LICENSE
streamlit_list_with_loader-0.1.3.dist-info/METADATA
streamlit_list_with_loader-0.1.3.dist-info/WHEEL
streamlit_list_with_loader-0.1.3.dist-info/top_level.txt
streamlit_list_with_loader-0.1.3.dist-info/RECORD
