Metadata-Version: 2.1
Name: streamlit-list-with-loader
Version: 0.1.3
Summary: A streamlist component that allows you to have a liist with loading status
Author: Firdaus A. Indradhirmaya
Author-email: fai14@pitt.edu
Requires-Python: >=3.7
License-File: LICENSE
Requires-Dist: streamlit >=1.2
Requires-Dist: jinja2
